datasette_export/__init__.py
datasette_export-0.1a0.dist-info/LICENSE
datasette_export-0.1a0.dist-info/METADATA
datasette_export-0.1a0.dist-info/WHEEL
datasette_export-0.1a0.dist-info/entry_points.txt
datasette_export-0.1a0.dist-info/top_level.txt
datasette_export-0.1a0.dist-info/RECORD
