Metadata-Version: 2.1
Name: datasette-export
Version: 0.1a0
Summary: Export pages from Datasette to files on disk
Home-page: https://github.com/simonw/datasette-export
Author: Simon Willison
License: Apache License, Version 2.0
Project-URL: Issues, https://github.com/simonw/datasette-export/issues
Project-URL: CI, https://github.com/simonw/datasette-export/actions
Project-URL: Changelog, https://github.com/simonw/datasette-export/releases
Classifier: Framework :: Datasette
Classifier: License :: OSI Approved :: Apache Software License
Requires-Python: >=3.7
License-File: LICENSE
Requires-Dist: datasette
Provides-Extra: test
Requires-Dist: pytest ; extra == 'test'
Requires-Dist: pytest-asyncio ; extra == 'test'
